{
  "date": "2026-06-28",
  "prev_date": "2026-06-27",
  "periods": {
    "7": {
      "period": "近 7 日",
      "source": "rule",
      "summary": "近 7 日里，古风言情、幻想言情 是更热的综合赛道，具体分类以 女频悬疑、古风世情、女频衍生 的榜单动能更强；题材上 系统、重生、双洁、女配、空间、末世 反复出现，说明读者仍偏好强设定、强情绪钩子和明确爽点。",
      "fallback_summary": "近 7 日里，古风言情、幻想言情 是更热的综合赛道，具体分类以 女频悬疑、古风世情、女频衍生 的榜单动能更强；题材上 系统、重生、双洁、女配、空间、末世 反复出现，说明读者仍偏好强设定、强情绪钩子和明确爽点。",
      "hot_genres": [
        {
          "name": "古风言情",
          "score": 732,
          "new_count": 45,
          "dropped_count": 45,
          "read_count": 84,
          "active_days": 28,
          "lead_category": "古风世情",
          "categories": [
            "古风世情",
            "古言脑洞",
            "宫斗宅斗",
            "种田"
          ]
        },
        {
          "name": "幻想言情",
          "score": 710,
          "new_count": 44,
          "dropped_count": 44,
          "read_count": 84,
          "active_days": 28,
          "lead_category": "女频悬疑",
          "categories": [
            "玄幻言情",
            "科幻末世",
            "悬疑脑洞",
            "女频悬疑"
          ]
        },
        {
          "name": "现代言情",
          "score": 646,
          "new_count": 32,
          "dropped_count": 32,
          "read_count": 84,
          "active_days": 28,
          "lead_category": "现言脑洞",
          "categories": [
            "现言脑洞",
            "豪门总裁",
            "职场婚恋",
            "青春甜宠"
          ]
        },
        {
          "name": "快穿衍生",
          "score": 376,
          "new_count": 24,
          "dropped_count": 24,
          "read_count": 42,
          "active_days": 14,
          "lead_category": "女频衍生",
          "categories": [
            "快穿",
            "女频衍生"
          ]
        },
        {
          "name": "年代民国",
          "score": 344,
          "new_count": 19,
          "dropped_count": 19,
          "read_count": 42,
          "active_days": 14,
          "lead_category": "年代",
          "categories": [
            "年代",
            "民国言情"
          ]
        }
      ],
      "hot_types": [
        {
          "name": "女频悬疑",
          "score": 206,
          "new_count": 16,
          "dropped_count": 16,
          "read_count": 21,
          "active_days": 7
        },
        {
          "name": "古风世情",
          "score": 200,
          "new_count": 14,
          "dropped_count": 14,
          "read_count": 21,
          "active_days": 7
        },
        {
          "name": "女频衍生",
          "score": 200,
          "new_count": 14,
          "dropped_count": 14,
          "read_count": 21,
          "active_days": 7
        },
        {
          "name": "玄幻言情",
          "score": 188,
          "new_count": 12,
          "dropped_count": 12,
          "read_count": 21,
          "active_days": 7
        },
        {
          "name": "种田",
          "score": 188,
          "new_count": 12,
          "dropped_count": 12,
          "read_count": 21,
          "active_days": 7
        },
        {
          "name": "科幻末世",
          "score": 182,
          "new_count": 12,
          "dropped_count": 12,
          "read_count": 21,
          "active_days": 7
        }
      ],
      "hot_themes": [
        {
          "name": "系统",
          "count": 148,
          "category_count": 16
        },
        {
          "name": "重生",
          "count": 112,
          "category_count": 18
        },
        {
          "name": "双洁",
          "count": 83,
          "category_count": 14
        },
        {
          "name": "女配",
          "count": 81,
          "category_count": 14
        },
        {
          "name": "空间",
          "count": 76,
          "category_count": 12
        },
        {
          "name": "末世",
          "count": 64,
          "category_count": 6
        },
        {
          "name": "反派",
          "count": 63,
          "category_count": 13
        },
        {
          "name": "快穿",
          "count": 58,
          "category_count": 4
        },
        {
          "name": "年代",
          "count": 50,
          "category_count": 5
        },
        {
          "name": "炮灰",
          "count": 48,
          "category_count": 11
        },
        {
          "name": "团宠",
          "count": 45,
          "category_count": 13
        },
        {
          "name": "甜宠",
          "count": 43,
          "category_count": 12
        },
        {
          "name": "直播",
          "count": 40,
          "category_count": 6
        },
        {
          "name": "逃荒",
          "count": 39,
          "category_count": 3
        }
      ]
    },
    "14": {
      "period": "近 14 日",
      "source": "rule",
      "summary": "近 14 日里，古风言情、幻想言情 是更热的综合赛道，具体分类以 快穿、古言脑洞、古风世情 的榜单动能更强；题材上 重生、系统、女配、空间、末世、双洁 反复出现，说明读者仍偏好强设定、强情绪钩子和明确爽点。",
      "fallback_summary": "近 14 日里，古风言情、幻想言情 是更热的综合赛道，具体分类以 快穿、古言脑洞、古风世情 的榜单动能更强；题材上 重生、系统、女配、空间、末世、双洁 反复出现，说明读者仍偏好强设定、强情绪钩子和明确爽点。",
      "hot_genres": [
        {
          "name": "古风言情",
          "score": 1420,
          "new_count": 83,
          "dropped_count": 83,
          "read_count": 168,
          "active_days": 56,
          "lead_category": "古言脑洞",
          "categories": [
            "古风世情",
            "古言脑洞",
            "宫斗宅斗",
            "种田"
          ]
        },
        {
          "name": "幻想言情",
          "score": 1390,
          "new_count": 82,
          "dropped_count": 82,
          "read_count": 168,
          "active_days": 56,
          "lead_category": "玄幻言情",
          "categories": [
            "玄幻言情",
            "科幻末世",
            "悬疑脑洞",
            "女频悬疑"
          ]
        },
        {
          "name": "现代言情",
          "score": 1344,
          "new_count": 73,
          "dropped_count": 73,
          "read_count": 168,
          "active_days": 56,
          "lead_category": "现言脑洞",
          "categories": [
            "现言脑洞",
            "豪门总裁",
            "职场婚恋",
            "青春甜宠"
          ]
        },
        {
          "name": "快穿衍生",
          "score": 754,
          "new_count": 49,
          "dropped_count": 49,
          "read_count": 84,
          "active_days": 28,
          "lead_category": "快穿",
          "categories": [
            "快穿",
            "女频衍生"
          ]
        },
        {
          "name": "年代民国",
          "score": 686,
          "new_count": 38,
          "dropped_count": 38,
          "read_count": 84,
          "active_days": 28,
          "lead_category": "年代",
          "categories": [
            "年代",
            "民国言情"
          ]
        }
      ],
      "hot_types": [
        {
          "name": "快穿",
          "score": 385,
          "new_count": 26,
          "dropped_count": 26,
          "read_count": 42,
          "active_days": 14
        },
        {
          "name": "古言脑洞",
          "score": 373,
          "new_count": 24,
          "dropped_count": 24,
          "read_count": 42,
          "active_days": 14
        },
        {
          "name": "古风世情",
          "score": 369,
          "new_count": 23,
          "dropped_count": 23,
          "read_count": 42,
          "active_days": 14
        },
        {
          "name": "女频衍生",
          "score": 369,
          "new_count": 23,
          "dropped_count": 23,
          "read_count": 42,
          "active_days": 14
        },
        {
          "name": "年代",
          "score": 369,
          "new_count": 23,
          "dropped_count": 23,
          "read_count": 42,
          "active_days": 14
        },
        {
          "name": "玄幻言情",
          "score": 363,
          "new_count": 22,
          "dropped_count": 22,
          "read_count": 42,
          "active_days": 14
        }
      ],
      "hot_themes": [
        {
          "name": "重生",
          "count": 164,
          "category_count": 18
        },
        {
          "name": "系统",
          "count": 158,
          "category_count": 16
        },
        {
          "name": "女配",
          "count": 113,
          "category_count": 14
        },
        {
          "name": "空间",
          "count": 102,
          "category_count": 13
        },
        {
          "name": "末世",
          "count": 87,
          "category_count": 6
        },
        {
          "name": "双洁",
          "count": 83,
          "category_count": 14
        },
        {
          "name": "快穿",
          "count": 81,
          "category_count": 5
        },
        {
          "name": "反派",
          "count": 77,
          "category_count": 15
        },
        {
          "name": "炮灰",
          "count": 68,
          "category_count": 11
        },
        {
          "name": "年代",
          "count": 61,
          "category_count": 5
        },
        {
          "name": "团宠",
          "count": 60,
          "category_count": 13
        },
        {
          "name": "强制爱",
          "count": 56,
          "category_count": 11
        },
        {
          "name": "逃荒",
          "count": 45,
          "category_count": 3
        },
        {
          "name": "甜宠",
          "count": 44,
          "category_count": 13
        }
      ]
    },
    "30": {
      "period": "近 30 日",
      "source": "rule",
      "summary": "近 30 日里，古风言情、幻想言情 是更热的综合赛道，具体分类以 女频衍生、宫斗宅斗、玄幻言情 的榜单动能更强；题材上 重生、系统、女配、快穿、空间、反派 反复出现，说明读者仍偏好强设定、强情绪钩子和明确爽点。",
      "fallback_summary": "近 30 日里，古风言情、幻想言情 是更热的综合赛道，具体分类以 女频衍生、宫斗宅斗、玄幻言情 的榜单动能更强；题材上 重生、系统、女配、快穿、空间、反派 反复出现，说明读者仍偏好强设定、强情绪钩子和明确爽点。",
      "hot_genres": [
        {
          "name": "古风言情",
          "score": 3058,
          "new_count": 181,
          "dropped_count": 181,
          "read_count": 360,
          "active_days": 120,
          "lead_category": "宫斗宅斗",
          "categories": [
            "古风世情",
            "古言脑洞",
            "宫斗宅斗",
            "种田"
          ]
        },
        {
          "name": "幻想言情",
          "score": 2942,
          "new_count": 167,
          "dropped_count": 167,
          "read_count": 360,
          "active_days": 120,
          "lead_category": "玄幻言情",
          "categories": [
            "玄幻言情",
            "科幻末世",
            "悬疑脑洞",
            "女频悬疑"
          ]
        },
        {
          "name": "现代言情",
          "score": 2902,
          "new_count": 160,
          "dropped_count": 160,
          "read_count": 360,
          "active_days": 120,
          "lead_category": "现言脑洞",
          "categories": [
            "现言脑洞",
            "豪门总裁",
            "职场婚恋",
            "青春甜宠"
          ]
        },
        {
          "name": "快穿衍生",
          "score": 1588,
          "new_count": 100,
          "dropped_count": 100,
          "read_count": 180,
          "active_days": 60,
          "lead_category": "女频衍生",
          "categories": [
            "快穿",
            "女频衍生"
          ]
        },
        {
          "name": "年代民国",
          "score": 1484,
          "new_count": 86,
          "dropped_count": 86,
          "read_count": 180,
          "active_days": 60,
          "lead_category": "年代",
          "categories": [
            "年代",
            "民国言情"
          ]
        }
      ],
      "hot_types": [
        {
          "name": "女频衍生",
          "score": 813,
          "new_count": 53,
          "dropped_count": 53,
          "read_count": 90,
          "active_days": 30
        },
        {
          "name": "宫斗宅斗",
          "score": 795,
          "new_count": 50,
          "dropped_count": 50,
          "read_count": 90,
          "active_days": 30
        },
        {
          "name": "玄幻言情",
          "score": 781,
          "new_count": 48,
          "dropped_count": 48,
          "read_count": 90,
          "active_days": 30
        },
        {
          "name": "种田",
          "score": 781,
          "new_count": 48,
          "dropped_count": 48,
          "read_count": 90,
          "active_days": 30
        },
        {
          "name": "年代",
          "score": 781,
          "new_count": 48,
          "dropped_count": 48,
          "read_count": 90,
          "active_days": 30
        },
        {
          "name": "快穿",
          "score": 775,
          "new_count": 47,
          "dropped_count": 47,
          "read_count": 90,
          "active_days": 30
        }
      ],
      "hot_themes": [
        {
          "name": "重生",
          "count": 246,
          "category_count": 18
        },
        {
          "name": "系统",
          "count": 235,
          "category_count": 18
        },
        {
          "name": "女配",
          "count": 169,
          "category_count": 15
        },
        {
          "name": "快穿",
          "count": 153,
          "category_count": 6
        },
        {
          "name": "空间",
          "count": 147,
          "category_count": 16
        },
        {
          "name": "反派",
          "count": 133,
          "category_count": 16
        },
        {
          "name": "末世",
          "count": 131,
          "category_count": 9
        },
        {
          "name": "团宠",
          "count": 121,
          "category_count": 15
        },
        {
          "name": "炮灰",
          "count": 118,
          "category_count": 13
        },
        {
          "name": "穿书",
          "count": 100,
          "category_count": 15
        },
        {
          "name": "双洁",
          "count": 100,
          "category_count": 14
        },
        {
          "name": "强制爱",
          "count": 83,
          "category_count": 12
        },
        {
          "name": "甜宠",
          "count": 82,
          "category_count": 14
        },
        {
          "name": "年代",
          "count": 78,
          "category_count": 6
        }
      ]
    },
    "all": {
      "period": "全部样本",
      "source": "rule",
      "summary": "全部样本里，古风言情、现代言情 是更热的综合赛道，具体分类以 宫斗宅斗、女频衍生、快穿 的榜单动能更强；题材上 系统、重生、女配、穿书、快穿、团宠 反复出现，说明读者仍偏好强设定、强情绪钩子和明确爽点。",
      "fallback_summary": "全部样本里，古风言情、现代言情 是更热的综合赛道，具体分类以 宫斗宅斗、女频衍生、快穿 的榜单动能更强；题材上 系统、重生、女配、穿书、快穿、团宠 反复出现，说明读者仍偏好强设定、强情绪钩子和明确爽点。",
      "hot_genres": [
        {
          "name": "古风言情",
          "score": 8026,
          "new_count": 487,
          "dropped_count": 487,
          "read_count": 936,
          "active_days": 312,
          "lead_category": "宫斗宅斗",
          "categories": [
            "古风世情",
            "古言脑洞",
            "宫斗宅斗",
            "种田"
          ]
        },
        {
          "name": "现代言情",
          "score": 7712,
          "new_count": 438,
          "dropped_count": 438,
          "read_count": 936,
          "active_days": 312,
          "lead_category": "职场婚恋",
          "categories": [
            "现言脑洞",
            "豪门总裁",
            "职场婚恋",
            "青春甜宠"
          ]
        },
        {
          "name": "幻想言情",
          "score": 7540,
          "new_count": 414,
          "dropped_count": 414,
          "read_count": 936,
          "active_days": 312,
          "lead_category": "玄幻言情",
          "categories": [
            "玄幻言情",
            "科幻末世",
            "悬疑脑洞",
            "女频悬疑"
          ]
        },
        {
          "name": "快穿衍生",
          "score": 4112,
          "new_count": 258,
          "dropped_count": 258,
          "read_count": 468,
          "active_days": 156,
          "lead_category": "女频衍生",
          "categories": [
            "快穿",
            "女频衍生"
          ]
        },
        {
          "name": "年代民国",
          "score": 3810,
          "new_count": 214,
          "dropped_count": 214,
          "read_count": 468,
          "active_days": 156,
          "lead_category": "年代",
          "categories": [
            "年代",
            "民国言情"
          ]
        }
      ],
      "hot_types": [
        {
          "name": "宫斗宅斗",
          "score": 2117,
          "new_count": 139,
          "dropped_count": 139,
          "read_count": 234,
          "active_days": 78
        },
        {
          "name": "女频衍生",
          "score": 2065,
          "new_count": 130,
          "dropped_count": 130,
          "read_count": 234,
          "active_days": 78
        },
        {
          "name": "快穿",
          "score": 2047,
          "new_count": 128,
          "dropped_count": 128,
          "read_count": 234,
          "active_days": 78
        },
        {
          "name": "年代",
          "score": 2039,
          "new_count": 127,
          "dropped_count": 127,
          "read_count": 234,
          "active_days": 78
        },
        {
          "name": "古风世情",
          "score": 1989,
          "new_count": 118,
          "dropped_count": 118,
          "read_count": 234,
          "active_days": 78
        },
        {
          "name": "职场婚恋",
          "score": 1981,
          "new_count": 119,
          "dropped_count": 119,
          "read_count": 234,
          "active_days": 78
        }
      ],
      "hot_themes": [
        {
          "name": "系统",
          "count": 631,
          "category_count": 18
        },
        {
          "name": "重生",
          "count": 603,
          "category_count": 18
        },
        {
          "name": "女配",
          "count": 487,
          "category_count": 17
        },
        {
          "name": "穿书",
          "count": 393,
          "category_count": 17
        },
        {
          "name": "快穿",
          "count": 382,
          "category_count": 10
        },
        {
          "name": "团宠",
          "count": 341,
          "category_count": 15
        },
        {
          "name": "空间",
          "count": 313,
          "category_count": 18
        },
        {
          "name": "反派",
          "count": 300,
          "category_count": 18
        },
        {
          "name": "炮灰",
          "count": 295,
          "category_count": 15
        },
        {
          "name": "甜宠",
          "count": 282,
          "category_count": 18
        },
        {
          "name": "末世",
          "count": 279,
          "category_count": 13
        },
        {
          "name": "无CP",
          "count": 264,
          "category_count": 18
        },
        {
          "name": "强制爱",
          "count": 238,
          "category_count": 16
        },
        {
          "name": "双洁",
          "count": 181,
          "category_count": 16
        }
      ]
    }
  }
}